{
  "dares": [
    {
      "id": 1,
      "text": "ุบูู ุงููุดูุฏ ุงููุทูู ูุจูุฏ ููุงูุณู ุจุตูุช ุนุงูู! ๐ค",
      "difficulty": "easy",
      "category": "ุบูุงุก"
    },
    {
      "id": 2,
      "text": "ุงุนูู 20 ุชูุฑูู ุถุบุท ุงูุขู! ๐ช",
      "difficulty": "medium",
      "category": "ุฑูุงุถุฉ"
    },
    {
      "id": 3,
      "text": "ููุฏ ุงุญุชูุงู ุฑููุงูุฏู 'ุณูููู' 5 ูุฑุงุช! โฝ",
      "difficulty": "easy",
      "category": "ุชูููุฏ"
    },
    {
      "id": 4,
      "text": "ุงูุดุฑ ุนูู ุงูุณูุดูุงู ููุฏูุง: 'ุฎุณุฑุช ูู ุชุญุฏู ูุฑุฉ ุงููุฏู ูู ุตุฏููู!' ๐ฑ",
      "difficulty": "hard",
      "category": "ุณูุดูุงู ููุฏูุง"
    },
    {
      "id": 5,
      "text": "ุงุดุชุฑู ูููุฉ ูููุงุฆุฒ ุงูุขู! โ",
      "difficulty": "medium",
      "category": "ููุงูุฃุฉ"
    },
    {
      "id": 6,
      "text": "ููุฏ ุตูุช ุงููุนูู ููู ูุตุฑุฎ 'ุฌูููููู!' 10 ูุฑุงุช! ๐ข",
      "difficulty": "easy",
      "category": "ุชูููุฏ"
    },
    {
      "id": 7,
      "text": "ุงูุจุณ ูููุต ุงููุฑูู ุงูููุงูุณ ููุฑููู ุงูููุถู ููุฏุฉ ุณุงุนุฉ! ๐",
      "difficulty": "hard",
      "category": "ููุงุจุณ"
    },
    {
      "id": 8,
      "text": "ุงูุชุจ ููุดูุฑ ุทููู ุนู ููุงุฐุง ุงููุงุฆุฒ ุฃูุถู ููู ูู ูุฑุฉ ุงููุฏู! โ๏ธ",
      "difficulty": "medium",
      "category": "ุณูุดูุงู ููุฏูุง"
    },
    {
      "id": 9,
      "text": "ุงุนูู 50 ููุฒุฉ ูู ุงูููุงู ุจุฃุณุฑุน ูุง ูููู! ๐",
      "difficulty": "medium",
      "category": "ุฑูุงุถุฉ"
    },
    {
      "id": 10,
      "text": "ููุฏ ูุดูุฉ ุฑููุงูุฏู ุงูุดููุฑุฉ ููุฏุฉ ุฏูููุฉ! ๐ถ",
      "difficulty": "easy",
      "category": "ุชูููุฏ"
    },
    {
      "id": 11,
      "text": "ุบูู ุฃุบููุฉ 'Waka Waka' ูุงููุฉ! ๐ต",
      "difficulty": "medium",
      "category": "ุบูุงุก"
    },
    {
      "id": 12,
      "text": "ุงุชุตู ุจุตุฏูู ููู ูู ุฃูู ุฃุณูุฃ ูุงุนุจ ูุฑุฉ ูุฏู ูู ุงูุชุงุฑูุฎ! ๐",
      "difficulty": "hard",
      "category": "ุงุชุตุงู"
    },
    {
      "id": 13,
      "text": "ุงุนูู 30 ูุฑูุตุงุก ุงูุขู! ๐ฆต",
      "difficulty": "medium",
      "category": "ุฑูุงุถุฉ"
    },
    {
      "id": 14,
      "text": "ุงุฑูุต ุฑูุตุฉ ูููุงุฑ ุงูุดููุฑุฉ! ๐",
      "difficulty": "easy",
      "category": "ุชูููุฏ"
    },
    {
      "id": 15,
      "text": "ุงูุชุจ ุงุณู ุงููุงุฆุฒ 10 ูุฑุงุช ุนูู ูุฑูุฉ ููู 'ุฃูุช ุงูุฃูุถู'! ๐",
      "difficulty": "easy",
      "category": "ูุชุงุจุฉ"
    },
    {
      "id": 16,
      "text": "ุงุดุฑุจ ููุจ ูุงุก ูุจูุฑ ุฏูุนุฉ ูุงุญุฏุฉ ุจุฏูู ุชููู! ๐ง",
      "difficulty": "easy",
      "category": "ุดุฑุจ"
    },
    {
      "id": 17,
      "text": "ูู ุนูู ุฑุฌู ูุงุญุฏุฉ ููุฏุฉ ุฏูููุชูู! ๐ฆถ",
      "difficulty": "medium",
      "category": "ุชูุงุฒู"
    },
    {
      "id": 18,
      "text": "ุงุนุชุฑู ุฃูุงู ุงูุฌููุน ุจุฃู ูุฑููู ุงูููุถู ููุณ ุงูุฃูุถู! ๐",
      "difficulty": "hard",
      "category": "ุงุนุชุฑุงู"
    },
    {
      "id": 19,
      "text": "ุงุนูู ุชูุซูููุฉ ูุญุงุฑุณ ูุฑูู ูุชููู 5 ุฃูุฏุงู! ๐ฅ",
      "difficulty": "medium",
      "category": "ุชูุซูู"
    },
    {
      "id": 20,
      "text": "ุบูู ูุดูุฏ ุฏูุฑู ุฃุจุทุงู ุฃูุฑูุจุง! ๐ถ",
      "difficulty": "medium",
      "category": "ุบูุงุก"
    },
    {
      "id": 21,
      "text": "ููุฏ ุงุญุชูุงู ูุญูุฏ ุตูุงุญ ุจุนุฏ ุงููุฏู! ๐",
      "difficulty": "easy",
      "category": "ุชูููุฏ"
    },
    {
      "id": 22,
      "text": "ุงุฌุฑู ูู ุงูููุงู ููุฏุฉ 3 ุฏูุงุฆู! ๐โโ๏ธ",
      "difficulty": "hard",
      "category": "ุฑูุงุถุฉ"
    },
    {
      "id": 23,
      "text": "ุงุตูุน ูุตูุฏุฉ ูู 4 ุฃุจูุงุช ุชูุฏุญ ูููุง ุงููุงุฆุฒ! ๐",
      "difficulty": "hard",
      "category": "ุฅุจุฏุงุน"
    },
    {
      "id": 24,
      "text": "ููุฏ ุงููุฏุฑุจ ุงูุบุงุถุจ ููู ูุตุฑุฎ ุนูู ุงููุงุนุจูู! ๐ค",
      "difficulty": "easy",
      "category": "ุชูููุฏ"
    },
    {
      "id": 25,
      "text": "ุงุฏูุน 5 ุฏูุงููุฑ/ุฏููุงุฑุงุช/ููุฑู ูููุงุฆุฒ! ๐ฐ",
      "difficulty": "hard",
      "category": "ููุงูุฃุฉ"
    },
    {
      "id": 26,
      "text": "ุงุนูู 15 ุชูุฑูู ุจูุฑุจู (burpees)! ๐คธ",
      "difficulty": "hard",
      "category": "ุฑูุงุถุฉ"
    },
    {
      "id": 27,
      "text": "ุงูุชูุท ุตูุฑุฉ ุณูููู ูุถุญูุฉ ูุฃุฑุณููุง ูู 5 ุฃุตุฏูุงุก! ๐คณ",
      "difficulty": "medium",
      "category": "ุตูุฑ"
    },
    {
      "id": 28,
      "text": "ููุฏ ุตูุช ููุดูุฉ ุญุงุฑุณ ุงููุฑูู ุจุนุฏ ุงุณุชูุจุงู ูุฏู! ๐งค",
      "difficulty": "easy",
      "category": "ุชูููุฏ"
    },
    {
      "id": 29,
      "text": "ุงุตุฑุฎ ูู ุงูุดุจุงู/ุงูุจุงุจ: 'ุฃูุง ุฎุณุฑุช ููุด ูุงูู ูู ุงูููุฑุฉ!' ๐ฃ",
      "difficulty": "hard",
      "category": "ุตุฑุงุฎ"
    },
    {
      "id": 30,
      "text": "ุงุนูู 25 ููุฒุฉ ุฌุงู (jumping jacks)! ๐คพ",
      "difficulty": "medium",
      "category": "ุฑูุงุถุฉ"
    },
    {
      "id": 31,
      "text": "ููุฏ ูุดูุฉ ููุณู ููู ููุดู ุจุงููุฑุฉ! โฝ",
      "difficulty": "easy",
      "category": "ุชูููุฏ"
    },
    {
      "id": 32,
      "text": "ุงุญูู ููุชุฉ ุนู ูุฑุฉ ุงููุฏู ูุงุถุญู ุนูููุง ุจุตูุช ุนุงูู ุญุชู ูู ูุง ูุงูุช ูุถุญูุฉ! ๐",
      "difficulty": "medium",
      "category": "ููููุฏูุง"
    },
    {
      "id": 33,
      "text": "ุงูุชุจ ุณุชูุฑู ุนูู ุงูุงูุณุชุบุฑุงู: 'ุชุญุฏู ุฎุณุฑุงู ูู ูุฑุฉ ุงููุฏู' ูุน ุตูุฑุชู! ๐ธ",
      "difficulty": "hard",
      "category": "ุณูุดูุงู ููุฏูุง"
    },
    {
      "id": 34,
      "text": "ุงุนูู ุจูุงูู (plank) ููุฏุฉ ุฏูููุฉ! ๐๏ธ",
      "difficulty": "medium",
      "category": "ุฑูุงุถุฉ"
    },
    {
      "id": 35,
      "text": "ุบูู ุฃุบููุฉ 'ููููู ูุงุจ' (Wavin' Flag) ุจุงูุฅูุฌููุฒูุฉ! ๐ค",
      "difficulty": "hard",
      "category": "ุบูุงุก"
    },
    {
      "id": 36,
      "text": "ููุฏ ุงุญุชูุงู ูุฑูุณุชูุงูู ุฑููุงูุฏู ุงููุงูู! ๐ฏ",
      "difficulty": "easy",
      "category": "ุชูููุฏ"
    },
    {
      "id": 37,
      "text": "ุงูุชุจ ุนูู ุฌุจูุชู 'ุฎุณุฑุงู' ูุงุชุฑู ููุฏุฉ 5 ุฏูุงุฆู! โ๏ธ",
      "difficulty": "hard",
      "category": "ุฑุณู"
    },
    {
      "id": 38,
      "text": "ุงุนูู 40 ูุท ุงูุญุจู (ุฃู ุญุฑูุงุช ูุท)! ๐ชข",
      "difficulty": "medium",
      "category": "ุฑูุงุถุฉ"
    },
    {
      "id": 39,
      "text": "ููุฏ ุงููุนูู ููู ูุตู ูุฏู ุฑุงุฆุน ููุฏุฉ ุฏูููุฉ! ๐๏ธ",
      "difficulty": "medium",
      "category": "ุชูููุฏ"
    },
    {
      "id": 40,
      "text": "ุงุนุชุฑู ุจุฃู ุงููุงุฆุฒ ูุนุฑู ุฃูุซุฑ ููู ูู ูุฑุฉ ุงููุฏู! ๐",
      "difficulty": "easy",
      "category": "ุงุนุชุฑุงู"
    }
  ]
}
